{
  "apia": "1.0",
  "service": {
    "id": "perspective-api",
    "name": "Perspective API (Google Jigsaw)",
    "description_for_ai": "Free content moderation API from Google. Detects toxic comments, threats, insults, profanity, identity attacks. 100+ languages. Free. Used by New York Times, Wikipedia. Use for comment moderation.",
    "url": "https://perspectiveapi.com",
    "api_base": "https://commentanalyzer.googleapis.com/v1alpha1",
    "category": "ai_media",
    "geo": [
      "GLOBAL"
    ],
    "language": "en",
    "docs": "https://developers.perspectiveapi.com/s/docs"
  },
  "auth": {
    "type": "apikey",
    "anonymous_access": false,
    "param_name": "key",
    "param_location": "query",
    "how_to_get": "Request access at https://developers.perspectiveapi.com/s/request-quota",
    "cost": "Free with quota"
  },
  "capabilities": [
    {
      "id": "analyze_comment",
      "description_for_ai": "Score a comment for toxicity, threats, insults, profanity, identity attacks. Returns probability scores 0-1 for each requested attribute. Free. 100+ languages.",
      "intent": [
        "toxic comment",
        "moderation check",
        "hate speech detection",
        "comment score",
        "is this toxic",
        "offensive content",
        "content moderation",
        "проверка токсичности",
        "модерация"
      ],
      "endpoint": "POST https://commentanalyzer.googleapis.com/v1alpha1/comments:analyze",
      "input": {
        "comment": {
          "type": "object",
          "description": "{text: 'Comment text to analyze'}",
          "required": true
        },
        "requestedAttributes": {
          "type": "object",
          "description": "Attributes to score: {TOXICITY: {}, SEVERE_TOXICITY: {}, THREAT: {}, INSULT: {}, PROFANITY: {}, IDENTITY_ATTACK: {}, SEXUALLY_EXPLICIT: {}, FLIRTATION: {}}. Request only what you need.",
          "required": true
        },
        "languages": {
          "type": "array",
          "description": "Language codes: ['en', 'ru', 'de', 'fr', 'es', 'it', 'pt', 'zh']. Auto-detected if omitted.",
          "required": false
        },
        "doNotStore": {
          "type": "boolean",
          "description": "Set true to prevent Google from storing the comment",
          "default": false
        },
        "sessionId": {
          "type": "string",
          "description": "Opaque session identifier for tracking",
          "required": false
        }
      },
      "output": {
        "type": "scores",
        "fields": [
          "attributeScores.TOXICITY.summaryScore.value (0-1)",
          "attributeScores.SEVERE_TOXICITY.summaryScore.value",
          "attributeScores.THREAT.summaryScore.value",
          "attributeScores.INSULT.summaryScore.value",
          "attributeScores.PROFANITY.summaryScore.value",
          "attributeScores.IDENTITY_ATTACK.summaryScore.value"
        ]
      },
      "realtime": true,
      "requires_auth": true
    }
  ],
  "agent_hints": {
    "thresholds": "Common thresholds: score > 0.7 = block/reject, 0.5-0.7 = review queue, < 0.5 = allow. Adjust per your use case.",
    "free": "Completely free API with quota. Apply at https://perspectiveapi.com for production quota increase.",
    "languages": "TOXICITY works for 100+ languages. Other attributes have varying language support — check docs.",
    "privacy": "Set doNotStore: true for GDPR compliance. Comments with doNotStore are not used to train models."
  },
  "meta": {
    "apia_version": "1.0",
    "manifest_author": "APIA community",
    "last_verified": "2026-06-14"
  }
}